k8s_smuggler/__init__.py
k8s_smuggler/actions/__init__.py
k8s_smuggler/actions/config.py
k8s_smuggler/actions/migrate.py
k8s_smuggler/actions/version.py
k8s_smuggler/cli/__init__.py
k8s_smuggler/cli/config_file.py
k8s_smuggler/cli/logs.py
k8s_smuggler/cli/prompt.py
k8s_smuggler/cli/runtime.py
k8s_smuggler/cli/signals.py
k8s_smuggler/cli/visual.py
k8s_smuggler/commands/__init__.py
k8s_smuggler/commands/config.py
k8s_smuggler/commands/entrypoint.py
k8s_smuggler/commands/migrate.py
k8s_smuggler/commands/version.py
k8s_smuggler/configuration.py
k8s_smuggler/kubernetes/__init__.py
k8s_smuggler/kubernetes/client.py
k8s_smuggler/kubernetes/mappings.py
k8s_smuggler/kubernetes/sanitization.py
k8s_smuggler/lib/__init__.py
k8s_smuggler/lib/base_config.py
k8s_smuggler/main.py
k8s_smuggler-0.0.1.dist-info/entry_points.txt
k8s_smuggler-0.0.1.dist-info/METADATA
k8s_smuggler-0.0.1.dist-info/WHEEL
k8s_smuggler-0.0.1.dist-info/RECORD
