Metadata-Version: 2.1
Name: k8s-smuggler
Version: 0.0.1
Summary: 
Author: DiegoPomares
Requires-Python: >=3.10,<4.0
Classifier: Programming Language :: Python :: 3
Classifier: Programming Language :: Python :: 3.10
Classifier: Programming Language :: Python :: 3.11
Requires-Dist: click (>=8.1.3,<9.0.0)
Requires-Dist: kubernetes (>=23,<24)
